shoppy/__init__.py
shoppy/mixins.py
shoppy/resource_client.py
shoppy/resources.py
shoppy-1.0.dist-info/METADATA
shoppy-1.0.dist-info/WHEEL
shoppy-1.0.dist-info/top_level.txt
shoppy-1.0.dist-info/RECORD
