Metadata-Version: 2.1
Name: shoppy
Version: 1.0
Summary: Python shoppy.gg API client
Home-page: https://github.com/Qwizi/Shoppy-python
Author: Adrian 'Qwizi' Ciołek
License: MIT
Platform: UNKNOWN
Classifier: Programming Language :: Python :: 3
Classifier: License :: OSI Approved :: MIT License
Classifier: Operating System :: OS Independent
Requires-Python: >=3.7
